pyfpa/__init__.py
pyfpa/pyfpa.py
pyfpa-0.0.9.dist-info/LICENSE
pyfpa-0.0.9.dist-info/METADATA
pyfpa-0.0.9.dist-info/WHEEL
pyfpa-0.0.9.dist-info/top_level.txt
pyfpa-0.0.9.dist-info/RECORD
