Metadata-Version: 2.1
Name: pyfpa
Version: 0.0.9
Summary: Leverage the power of Python for corporate finance and accounting functions.
Home-page: https://github.com/warrenpilot/pyfpa
Author: Erik Warren
Author-email: erikwarren@yahoo.com
License: UNKNOWN
Platform: UNKNOWN
Classifier: Programming Language :: Python :: 3
Classifier: License :: OSI Approved :: MIT License
Classifier: Environment :: Win32 (MS Windows)
Classifier: Operating System :: Microsoft :: Windows :: Windows 10
Classifier: Development Status :: 4 - Beta
Classifier: Intended Audience :: Financial and Insurance Industry
Classifier: Topic :: Office/Business
Requires-Python: >=3.6
Requires-Dist: pandas (>=1.0.0)
Requires-Dist: numpy (>=1.17)
Requires-Dist: xlrd (>=1.0)
Requires-Dist: openpyxl (>=3.0)
Requires-Dist: pandas-bokeh (>=0.5.2)
